setup.py
getgithub/__init__.py
getgithub/conv.py
getgithub.egg-info/PKG-INFO
getgithub.egg-info/SOURCES.txt
getgithub.egg-info/dependency_links.txt
getgithub.egg-info/not-zip-safe
getgithub.egg-info/requires.txt
getgithub.egg-info/top_level.txt