Metadata-Version: 1.1
Name: getgithub
Version: 0.1
Summary: Convert JSON format to XML of the GitHub API
Home-page: https://github.com/alvarenga/getgithub
Author: Edson Alvarenga
Author-email: alvarenga.edson@gmail.com
License: BSD
Platform: UNKNOWN
Classifier: Development Status :: 4 - Beta
Classifier: Environment :: Web Environment
Classifier: Intended Audience :: Developers
Classifier: License :: OSI Approved :: BSD License
Classifier: Operating System :: OS Independent
Classifier: Programming Language :: Python
Classifier: Framework :: Paste
